modules/modules_base/hdl/defines.vh
//-------------------------------------------------
// Generated defines                               
//-------------------------------------------------

`define SIM 1

modules/modules/hdl/random_number_generator.v
`default_nettype none
//-----------------------------------------------------
// Project Name : a.out
// Function     : Generate random number
// Description  : Generate a random number and send by the output

//***Headers***
`include "defines.vh"
//***Module***
module random_number_generator #(
        parameter integer WORD_SIZE = 32
    )
    (
        input  clk_i ,
        output [WORD_SIZE - 1 : 0] output_number_o 
    );

//***Interal logic generated by compiler***  


//***Dumped Internal logic***
    assign output_number_o =  32'b00000001010000100100101111001001;
    //assign output_number_o = 32'b00100110011111101110111100010000  ;
    
//***Handcrafted Internal logic*** 
//TODO
endmodule

modules/modules_base/hdl/hash_cache_function.v
`default_nettype none
//-----------------------------------------------------
// Project Name : a.out
// Function     : Generate the hash function
// Description  : Generate all function

//***Headers***
`include "defines.vh"
//***Module***
module hash_cache_function #(
        parameter integer WORD_SIZE = 32
    )
    (
        input  clk_i ,
        input  [WORD_SIZE - 1 : 0] addr_i ,
        output line_index_o 
    );

//***Interal logic generated by compiler***  
//***Auxiliar Wires***  
    wire [WORD_SIZE - 1 : 0] random_number_w; // Auxiliar Wire

    random_number_generator #(
        .WORD_SIZE (32)
    )
    inst_RNG(
        .clk_i                  (clk_i ),
        .output_number_o        (random_number_w)
    );


//***Dumped Internal logic***
    reg [WORD_SIZE-1:0] rotate_0;
    reg [WORD_SIZE-1:0] rotate_1;
    reg [WORD_SIZE-1:0] rotate_2;
    reg [WORD_SIZE-1:0] rotate_3;
    reg [WORD_SIZE-1:0] rotate_4;
    reg [WORD_SIZE-1:0] rotate_5;
    wire [(WORD_SIZE*3)-1:0] output_xor_0;
    wire [48-1:0] output_xor_1;
    wire [24-1:0] output_xor_2;
    wire [12-1:0] output_xor_3;
    wire [6-1:0] output_xor_4;
    wire [3-1:0] output_xor_5;
    wire output_xor_6;
    

    assign output_xor_0 = {rotate_0,rotate_1,rotate_2} ^ {rotate_3,rotate_4,rotate_5};
    assign output_xor_1 = output_xor_0[95:48] ^ output_xor_0[47:0];
    assign output_xor_2 = output_xor_1[47:24] ^ output_xor_1[23:0];
    assign output_xor_3 = output_xor_2[23:12] ^ output_xor_2[11:0];
    assign output_xor_4 = output_xor_3[11:6] ^ output_xor_3[5:0];
    assign output_xor_5 = output_xor_4[5:3] ^ output_xor_4[2:0];
    assign line_index_o = output_xor_5[2] ^ output_xor_5[1] ^ output_xor_5[0];

    always @(posedge clk_i) begin


    rotate_0  <= (random_number_w >> addr_i[11:7]) | (random_number_w <<  (WORD_SIZE - {{27{1'b0}},addr_i[11:7]}));
    rotate_1  <= (random_number_w >> addr_i[16:12]) | (random_number_w <<  (WORD_SIZE - {{27{1'b0}},addr_i[16:12]}));
    rotate_2  <= (random_number_w >> addr_i[21:17]) | (random_number_w <<  (WORD_SIZE - {{27{1'b0}},addr_i[21:17]}));

    rotate_3  <= ({addr_i[31:7],7'b0000000} >> random_number_w[4:0]) | ({addr_i[31:7],7'b0000000} <<  (WORD_SIZE - {{27{1'b0}},random_number_w[4:0]}));
    rotate_4  <= ({addr_i[31:7],7'b0000000} >> random_number_w[9:5]) | ({addr_i[31:7],7'b0000000} <<  (WORD_SIZE - {{27{1'b0}},random_number_w[9:5]}));
    rotate_5  <= ({addr_i[31:7],7'b0000000} >> random_number_w[14:10]) | ({addr_i[31:7],7'b0000000} <<  (WORD_SIZE - {{27{1'b0}},random_number_w[14:10]}));



    end


    
//***Handcrafted Internal logic*** 
//TODO
endmodule

modules/modules/tb/verilator/obj_dir/Vhash_cache_function.vcd
$version Generated by VerilatedVcd $end
$date Tue Nov 12 12:35:39 2019
 $end
$timescale   1ns $end

 $scope module TOP $end
  $var wire 32 3 addr_i [31:0] $end
  $var wire  1 2 clk_i $end
  $var wire  1 4 line_index_o $end
  $scope module hash_cache_function $end
   $var wire 32 5 WORD_SIZE [31:0] $end
   $var wire 32 3 addr_i [31:0] $end
   $var wire  1 2 clk_i $end
   $var wire  1 4 line_index_o $end
   $var wire 96 # output_xor_0 [95:0] $end
   $var wire 48 & output_xor_1 [47:0] $end
   $var wire 24 ( output_xor_2 [23:0] $end
   $var wire 12 ) output_xor_3 [11:0] $end
   $var wire  6 * output_xor_4 [5:0] $end
   $var wire  3 + output_xor_5 [2:0] $end
   $var wire  1 7 output_xor_6 $end
   $var wire 32 6 random_number_w [31:0] $end
   $var wire 32 , rotate_0 [31:0] $end
   $var wire 32 - rotate_1 [31:0] $end
   $var wire 32 . rotate_2 [31:0] $end
   $var wire 32 / rotate_3 [31:0] $end
   $var wire 32 0 rotate_4 [31:0] $end
   $var wire 32 1 rotate_5 [31:0] $end
   $scope module inst_RNG $end
    $var wire 32 5 WORD_SIZE [31:0] $end
    $var wire  1 2 clk_i $end
    $var wire 32 6 output_number_o [31:0] $end
   $upscope $end
  $upscope $end
 $upscope $end
$enddefinitions $end


#0
b000000010100001001001011110010010000000101000010010010111100100100000001010000100100101111001001 #
b010010101000101101001010100010110100101010001011 &
b110000011100000111000001 (
b110111011101 )
b101010 *
b111 +
b00000001010000100100101111001001 ,
b00000001010000100100101111001001 -
b00000001010000100100101111001001 .
b00000000000000000000000000000000 /
b00000000000000000000000000000000 0
b00000000000000000000000000000000 1
12
b00000000000000000000000000000000 3
14
b00000000000000000000000000100000 5
b00000001010000100100101111001001 6
07
#1
02
#2
12
b00000000000000000000000000100000 3
#3
02
#4
12
b00000000000000000000000001000000 3
#5
02
#6
12
b00000000000000000000000001100000 3
#7
02
#8
b110000001010000100100101111001000000000101000010010010011100100100000001011000100100101111001001 #
b100010010110100000100100100001100100101010001011 &
b000011110010001010101111 (
b001001011101 )
b010100 *
b110 +
b10000000101000010010010111100100 ,
b01000000000000000000000000000000 /
b00000000000000000000001000000000 0
b00000000001000000000000000000000 1
12
b00000000000000000000000010000000 3
04
#9
02
#10
b100001010010001001011101100110111101111100000010011011100000001111001101001100100101010111101001 #
b111010110010000110010000101010011000101011101011 &
b010000101010101101111011 (
b111101010001 )
b101100 *
b001 +
b00000101000010010010111100100100 ,
b10000100100101111001001000000010 -
b10010010111100100100000001010000 .
b10000000001010110111001010111111 /
b01011011100101011111110000000001 0
b01011111110000000001010110111001 1
12
b01010110111001010111111100000000 3
14
#11
02
#12
b110000101010000000111000101001010000000101111100101101110010111000001100011100100001000011010011 #
b011101011000111000110100110101110001000110101111 &
b101000101001111110011011 (
b010110110010 )
b100100 *
b000 +
b00000010100001001001011110010010 ,
b00100100000001010000100100101111 -
b10010111100100100000001010000100 .
b11000000001001001010111100110111 /
b00100101011110011011111000000001 0
b10011011111000000001001001010111 1
12
b01001001010111100110111111001001 3
04
#13
02
#14
b110000101111101101101000011011011111110101111011011010011001000111111101011001001010100001101101 #
b101010110110101010010101000010010101010100010110 &
b101000100011111110000011 (
b010110100000 )
b110110 *
b00000010100001001001011110010010 -
b00000010100001001001011110010010 .
b11000000011111111111111111111111 /
b11111111111111111111111000000011 0
b11111111111000000011111111111111 1
12
b11111111111111111111111111111111 3
