modules/modules_base/hdl/defines.vh
//-------------------------------------------------
// Generated defines                               
//-------------------------------------------------

`define SIM 1

modules/modules/hdl/memory.v
`default_nettype none
//-----------------------------------------------------
// Project Name : a.out
// Function     : Memory emulator for the processor
// Description  : Memory simulation using a 32 bit size and a LINE_SIZE of 128 with a delay in 3 cycles for geting the data
// Coder        : Jaquer AND VORIXO

//***Headers***
`include "defines.vh"
//***Module***
module memory #(
        parameter integer WORD_SIZE = 32,
        parameter integer WORDS_PER_LINES = 4,
        parameter integer LINE_SIZE = 128,
        parameter integer MEMORY_LINES = 32
    )
    (
        input  clk_i ,
        input  rstn_i ,
        input  we_i ,
        input  strobe_i ,
        input  [LINE_SIZE - 1 : 0] data_i ,
        input  [WORD_SIZE - 1 : 0] addr_i ,
        output [LINE_SIZE - 1 : 0] data_o ,
        output valid_data_o 
    );

//***Interal logic generated by compiler***  


//***Dumped Internal logic***
    reg [WORD_SIZE-1:0] main_mem [0:MEMORY_LINES-1];
    reg [LINE_SIZE-1:0] data_o_0;
    reg [LINE_SIZE-1:0] data_o_1;
    reg [LINE_SIZE-1:0] data_o_2;
    reg [LINE_SIZE-1:0] data_o_3; 
    reg [LINE_SIZE-1:0] data_o_4;    
    reg valid_0; 
    reg valid_1;
    reg valid_2;
    reg valid_3;
    reg valid_4;
    `ifdef SIM
        initial begin
        $display("Loading rom.");
        $readmemh("../../../memory.hex", main_mem);
        $display("Rom loaded");
        end
    `endif

    always @(posedge clk_i) begin
        // data_o_0 <= {WORD_SIZE{1'b0}};
        valid_0 <=0;                           
        if (!rstn_i) begin                                       
            // reset                                            
            integer i;         
            /* verilator lint_off BLKLOOPINIT*/                                 
            for(i=0;i<MEMORY_LINES; i=i+1) begin                 
                main_mem[i] <= {WORD_SIZE{1'b0}};                
            end   
            /* verilator lint_on BLKLOOPINIT*/                                             
                                                                
        end                                                  
        else if (we_i) begin                                 
            main_mem[addr_i] <= data_i[31:0] ;                         
                                                                
        end else if (strobe_i) begin                        
            data_o_0[31:0] <=  main_mem[addr_i>>5]; 
            data_o_0[63:32] <= main_mem[(addr_i>>5)+1];
            data_o_0[95:64] <= main_mem[(addr_i>>5)+2];          
            data_o_0[127:96] <= main_mem[(addr_i>>5)+3]; 
            //data_o_0[31:0] <=  main_mem[addr_i];           
            //data_o_0[63:32] <= main_mem[addr_i + 2'b01];
            //data_o_0[95:64] <= main_mem[addr_i + 2'b10];                 
            //data_o_0[127:96] <= main_mem[addr_i + 2'b11]; 
            valid_0 <= 1;                    
                                                                
        end
        data_o <= data_o_4;
        valid_data_o <= valid_4;
        data_o_4 <=  data_o_3;
        valid_4 <= valid_3;
        data_o_3 <= data_o_2;
        valid_3 <= valid_2;
        data_o_2 <= data_o_1;
        valid_2 <= valid_1;
        data_o_1 <= data_o_0;
        valid_1 <= valid_0;

    end   
    
//***Handcrafted Internal logic*** 
//TODO
endmodule

modules/modules/hdl/fetch.v
`default_nettype none
//-----------------------------------------------------
// Project Name : a.out
// Function     : fetch instruction form the I-cache
// Description  : This module is for the feching instruction from the I-cahe in order to provided to the processor
// Coder        : Jaquer AND VORIXO

//***Headers***
`include "defines.vh"
//***Module***
module fetch #(
        parameter integer WORD_SIZE = 32,
        parameter integer LINE_SIZE = 128,
        parameter integer WORDS_PER_LINES = 4,
        parameter integer MEMORY_LINES = 4,
        parameter integer TAG = 24,
        parameter integer OFFSET = 7
    )
    (
        input  clk_i ,
        input  rstn_i ,
        input  [LINE_SIZE - 1 : 0] data_i ,
        input  valid_input_i ,
        output [WORD_SIZE - 1 : 0] nrm0_o ,
        output [WORD_SIZE - 1 : 0] addr_o ,
        output [WORD_SIZE - 1 : 0] instruction_register_o ,
        output ask_memory_o ,
        output valid_o 
    );

//***Interal logic generated by compiler***  


//***Dumped Internal logic***
    localparam NUM_SETS_CACHE = ((LINE_SIZE * MEMORY_LINES)/(LINE_SIZE *2));
    localparam WIDE_CACHE_LINE = (TAG*2 + LINE_SIZE*2 + 3);
    localparam INIT_POS_TAG_WAY_1 = 2;
    localparam INIT_POS_TAG_WAY_2 = 3+TAG+LINE_SIZE;
    localparam END_POS_TAG_WAY_1 = TAG+1;
    localparam END_POS_TAG_WAY_2 = TAG+2+LINE_SIZE+TAG;
    // params for cache word acces
    // way 1
    localparam INIT_POS_WORD_1_WAY_1 = TAG+2;
    localparam END_POS_WORD_1_WAY_1 = TAG+2+WORD_SIZE-1;
    localparam INIT_POS_WORD_2_WAY_1 = TAG+WORD_SIZE+2;
    localparam END_POS_WORD_2_WAY_1 = TAG+2+WORD_SIZE+WORD_SIZE-1;
    localparam INIT_POS_WORD_3_WAY_1 = TAG+WORD_SIZE+WORD_SIZE+2;
    localparam END_POS_WORD_3_WAY_1 = TAG+2+WORD_SIZE+WORD_SIZE+WORD_SIZE-1;
    localparam INIT_POS_WORD_4_WAY_1 = TAG+WORD_SIZE+WORD_SIZE+WORD_SIZE+2;
    localparam END_POS_WORD_4_WAY_1 = TAG+2+WORD_SIZE+WORD_SIZE+WORD_SIZE+WORD_SIZE-1;
    
    // way 2
    localparam INIT_POS_WORD_1_WAY_2 = TAG+TAG+3+LINE_SIZE;
    localparam END_POS_WORD_1_WAY_2 = TAG+3+TAG+LINE_SIZE+WORD_SIZE-1;
    localparam INIT_POS_WORD_2_WAY_2 = TAG+TAG+WORD_SIZE+3+LINE_SIZE;
    localparam END_POS_WORD_2_WAY_2 = TAG+3+TAG+LINE_SIZE+WORD_SIZE+WORD_SIZE-1;
    localparam INIT_POS_WORD_3_WAY_2 = TAG+TAG+WORD_SIZE+WORD_SIZE+3+LINE_SIZE;
    localparam END_POS_WORD_3_WAY_2 = TAG+3+TAG+LINE_SIZE+WORD_SIZE+WORD_SIZE+WORD_SIZE-1;
    localparam INIT_POS_WORD_4_WAY_2 = TAG+TAG+WORD_SIZE+WORD_SIZE+WORD_SIZE+3+LINE_SIZE;
    localparam END_POS_WORD_4_WAY_2 = TAG+3+TAG+LINE_SIZE+WORD_SIZE+WORD_SIZE+WORD_SIZE+WORD_SIZE-1;
    
    // block 0 --> block in way 0
    localparam INIT_POS_LINE_0 = TAG+2;
    localparam END_POS_LINE_0 = TAG+2+LINE_SIZE-1;
    localparam INIT_POS_TAG_LINE_0 = 2;
    localparam END_POS_TAG_LINE_0 = TAG+1;
    localparam VALID_BIT_WAY_0 = 1;

    // block 1

    localparam INIT_POS_LINE_1 = TAG+TAG+3+LINE_SIZE;
    localparam END_POS_LINE_1 = TAG+3+TAG+LINE_SIZE+LINE_SIZE-1;
    localparam INIT_POS_TAG_LINE_1 = 3+TAG+LINE_SIZE;
    localparam END_POS_TAG_LINE_1 = TAG+2+LINE_SIZE+TAG;
    localparam VALID_BIT_WAY_1 = TAG+2+LINE_SIZE;

    reg [WORD_SIZE-1:0]addr_asked;
    reg addr_ask;
    reg [WIDE_CACHE_LINE-1:0] cache_men [0:NUM_SETS_CACHE-1];

    reg [WORD_SIZE-1:0] rm0;


    //assign next_pc_w = !rstn_i ? {WORD_SIZE{1'b0}} : valid_o ? rm0 + 32 :  rm0;
    always @(posedge clk_i) begin

        ask_memory_o <= 1'b0;
        if (!rstn_i) begin                                       
            // reset                                            
            integer i;         
            /* verilator lint_off BLKLOOPINIT*/                                 
            for(i=0;i<NUM_SETS_CACHE; i=i+1) begin                 
                cache_men[i] <= {WIDE_CACHE_LINE{1'b0}};                
            end   
            /* verilator lint_on BLKLOOPINIT*/
            rm0 <= {WORD_SIZE{1'b0}};
        end
        else begin
            //rm0 <= next_pc_w;
            // take the rm0 and check if is in catch
            // check if is in way 1 or 0
            // check way 0 and valid 23/7
            if(cache_men[rm0[OFFSET]][END_POS_TAG_WAY_1:INIT_POS_TAG_WAY_1] == rm0[WORD_SIZE-1:OFFSET+1] && cache_men[rm0[OFFSET]][VALID_BIT_WAY_0]) begin
                // hit in way 0
                // rm0[WORD_SIZE-1:TAG] is offset
                valid_o <= 1;
                rm0 <= rm0 +32;
                nrm0_o <= rm0 +32;

                if(rm0[OFFSET-1:OFFSET-2] == 2'b00) begin
                    instruction_register_o <= cache_men[rm0[OFFSET]][END_POS_WORD_1_WAY_1:INIT_POS_WORD_1_WAY_1];
                end
                else if (rm0[OFFSET-1:OFFSET-2] == 2'b01) begin
                    instruction_register_o <= cache_men[rm0[OFFSET]][END_POS_WORD_2_WAY_1:INIT_POS_WORD_2_WAY_1];
                end

                else if (rm0[OFFSET-1:OFFSET-2] == 2'b10) begin
                    instruction_register_o <= cache_men[rm0[OFFSET]][END_POS_WORD_3_WAY_1:INIT_POS_WORD_3_WAY_1];
                end
                else if (rm0[OFFSET-1:OFFSET-2] == 2'b11)begin
                    instruction_register_o <= cache_men[rm0[OFFSET]][END_POS_WORD_4_WAY_1:INIT_POS_WORD_4_WAY_1];
                end


                
            end
            // check way 1 and valid 
            else if(cache_men[rm0[OFFSET]][END_POS_TAG_WAY_2:INIT_POS_TAG_WAY_2] == rm0[WORD_SIZE-1:OFFSET+1] && cache_men[rm0[OFFSET]][VALID_BIT_WAY_1]) begin
                // hit in way 1
                valid_o <= 1;
                rm0 <= rm0 +32;
                nrm0_o <= rm0 +32;

                if(rm0[OFFSET-1:OFFSET-2] == 2'b00) begin
                    instruction_register_o <= cache_men[rm0[OFFSET]][END_POS_WORD_1_WAY_2:INIT_POS_WORD_1_WAY_2];
                end
                else if (rm0[OFFSET-1:OFFSET-2] == 2'b01) begin
                    instruction_register_o <= cache_men[rm0[OFFSET]][END_POS_WORD_2_WAY_2:INIT_POS_WORD_2_WAY_2];
                end

                else if (rm0[OFFSET-1:OFFSET-2] == 2'b10) begin
                    instruction_register_o <= cache_men[rm0[OFFSET]][END_POS_WORD_3_WAY_2:INIT_POS_WORD_3_WAY_2];
                end
                else if (rm0[OFFSET-1:OFFSET-2] == 2'b11)begin
                    instruction_register_o <= cache_men[rm0[OFFSET]][END_POS_WORD_4_WAY_2:INIT_POS_WORD_4_WAY_2];
                end

                
            end
            else if (addr_ask && valid_input_i) begin
                if(cache_men[addr_asked[OFFSET]][0]) begin
                    // LRU == 1 replace way 1
                    // replace LRU
                    cache_men[addr_asked[OFFSET]][0] <= 1'b0;
                    // store block in way 1
                    cache_men[addr_asked[OFFSET]][END_POS_LINE_1:INIT_POS_LINE_1] <= data_i;
                    // set the valid bit
                    cache_men[addr_asked[OFFSET]][VALID_BIT_WAY_1] <= 1'b1;
                    // store the tag
                    cache_men[addr_asked[OFFSET]][END_POS_TAG_LINE_1:INIT_POS_TAG_LINE_1] <= addr_asked[WORD_SIZE-1:OFFSET+1];
                    // set the ask
                    addr_ask <= 1'b0;

                end
                else begin
                    // LRU == 0 replace way 0
                    // replace LRU
                    cache_men[addr_asked[OFFSET]][0] <= 1'b1;
                    // store block in way 0
                    cache_men[addr_asked[OFFSET]][END_POS_LINE_0:INIT_POS_LINE_0] <= data_i;
                    // set bit to valid
                    cache_men[addr_asked[OFFSET]][VALID_BIT_WAY_0] <= 1'b1;
                    //store the tag
                    cache_men[addr_asked[OFFSET]][END_POS_TAG_LINE_0:INIT_POS_TAG_LINE_0] <= addr_asked[WORD_SIZE-1:OFFSET+1];
                    // set the ask
                    addr_ask <= 1'b0;

                end
            end
            else if (addr_ask && rm0 == addr_asked) begin
                // same addr ask 
                valid_o <= 0;
            end
            else begin
                // Mis go to main memory
                addr_asked <= rm0;
                addr_ask <= 1'b1;
                valid_o <= 0;
                addr_o <= rm0;
                ask_memory_o <= 1'b1;

            end 
        end

    end
    //assign next_pc_w = !rstn_i ? {WORD_SIZE{1'b0}} : valid_o ? rm0 + 32 :  rm0;
    //assign nrm0_o = next_pc_w;
    
//***Handcrafted Internal logic*** 
//TODO
endmodule

modules/modules/hdl/processor.v
`default_nettype none
//-----------------------------------------------------
// Project Name : a.out
// Function     : Main processor 
// Description  : This is the main processor
// Coder        : Jaquer AND VORIXO

//***Headers***
`include "defines.vh"
//***Module***
module processor #(
        parameter integer WORD_SIZE = 32,
        parameter integer REGISTERS = 32,
        parameter integer LINE_SIZE = 128,
        parameter integer ALUOP_SIZE = 4,
        parameter integer REGDIRSIZE = 5
    )
    (
        input  clk_i ,
        input  rstn_i 
    );

//***Interal logic generated by compiler***  
    wire [WORD_SIZE - 1 : 0] addr_IF_MEM; // wiring between addr_o of module IF and addr_i of module MEM
    wire valid_data_MEM_IF; // wiring between valid_data_o of module MEM and valid_input_i of module IF
//***Auxiliar Wires***  
    wire [LINE_SIZE - 1 : 0] mem_data_bus_w; // Auxiliar Wire
    wire write_data_bus_mem_w; // Auxiliar Wire
    wire strobe_main_memory_w; // Auxiliar Wire

    fetch #(
        .WORD_SIZE (32),
        .LINE_SIZE (128),
        .WORDS_PER_LINES (4),
        .MEMORY_LINES (4),
        .TAG (24),
        .OFFSET (7)
    )
    inst_IF(
        .clk_i                        (clk_i ),
        .rstn_i                       (rstn_i ),
        .data_i                       (mem_data_bus_w),
        .valid_input_i                (valid_data_MEM_IF),
        .nrm0_o                       (),
        .addr_o                       (addr_IF_MEM),
        .instruction_register_o       (),
        .ask_memory_o                 (strobe_main_memory_w),
        .valid_o                      ()
    );

    memory #(
        .WORD_SIZE (32),
        .WORDS_PER_LINES (4),
        .LINE_SIZE (128),
        .MEMORY_LINES (32)
    )
    inst_MEM(
        .clk_i                (clk_i ),
        .rstn_i               (rstn_i ),
        .we_i                 (write_data_bus_mem_w),
        .strobe_i             (strobe_main_memory_w),
        .data_i               (mem_data_bus_w),
        .addr_i               (addr_IF_MEM),
        .data_o               (mem_data_bus_w),
        .valid_data_o         (valid_data_MEM_IF)
    );


//***Handcrafted Internal logic*** 
//TODO
endmodule

modules/modules/tb/verilator/obj_dir/Vprocessor.vcd
$version Generated by VerilatedVcd $end
$date Tue Nov  5 12:31:36 2019
 $end
$timescale   1ns $end

 $scope module TOP $end
  $var wire  1 !! clk_i $end
  $var wire  1 "! rstn_i $end
  $scope module processor $end
   $var wire 32 %! ALUOP_SIZE [31:0] $end
   $var wire 32 $! LINE_SIZE [31:0] $end
   $var wire 32 &! REGDIRSIZE [31:0] $end
   $var wire 32 #! REGISTERS [31:0] $end
   $var wire 32 #! WORD_SIZE [31:0] $end
   $var wire 32 C addr_IF_MEM [31:0] $end
   $var wire  1 !! clk_i $end
   $var wire 128 E mem_data_bus_w [127:0] $end
   $var wire  1 "! rstn_i $end
   $var wire  1 I strobe_main_memory_w $end
   $var wire  1 D valid_data_MEM_IF $end
   $var wire  1 '! write_data_bus_mem_w $end
   $scope module inst_IF $end
    $var wire 32 6! END_POS_LINE_0 [31:0] $end
    $var wire 32 >! END_POS_LINE_1 [31:0] $end
    $var wire 32 -! END_POS_TAG_LINE_0 [31:0] $end
    $var wire 32 .! END_POS_TAG_LINE_1 [31:0] $end
    $var wire 32 -! END_POS_TAG_WAY_1 [31:0] $end
    $var wire 32 .! END_POS_TAG_WAY_2 [31:0] $end
    $var wire 32 0! END_POS_WORD_1_WAY_1 [31:0] $end
    $var wire 32 8! END_POS_WORD_1_WAY_2 [31:0] $end
    $var wire 32 2! END_POS_WORD_2_WAY_1 [31:0] $end
    $var wire 32 :! END_POS_WORD_2_WAY_2 [31:0] $end
    $var wire 32 4! END_POS_WORD_3_WAY_1 [31:0] $end
    $var wire 32 <! END_POS_WORD_3_WAY_2 [31:0] $end
    $var wire 32 6! END_POS_WORD_4_WAY_1 [31:0] $end
    $var wire 32 >! END_POS_WORD_4_WAY_2 [31:0] $end
    $var wire 32 /! INIT_POS_LINE_0 [31:0] $end
    $var wire 32 7! INIT_POS_LINE_1 [31:0] $end
    $var wire 32 *! INIT_POS_TAG_LINE_0 [31:0] $end
    $var wire 32 ,! INIT_POS_TAG_LINE_1 [31:0] $end
    $var wire 32 *! INIT_POS_TAG_WAY_1 [31:0] $end
    $var wire 32 ,! INIT_POS_TAG_WAY_2 [31:0] $end
    $var wire 32 /! INIT_POS_WORD_1_WAY_1 [31:0] $end
    $var wire 32 7! INIT_POS_WORD_1_WAY_2 [31:0] $end
    $var wire 32 1! INIT_POS_WORD_2_WAY_1 [31:0] $end
    $var wire 32 9! INIT_POS_WORD_2_WAY_2 [31:0] $end
    $var wire 32 3! INIT_POS_WORD_3_WAY_1 [31:0] $end
    $var wire 32 ;! INIT_POS_WORD_3_WAY_2 [31:0] $end
    $var wire 32 5! INIT_POS_WORD_4_WAY_1 [31:0] $end
    $var wire 32 =! INIT_POS_WORD_4_WAY_2 [31:0] $end
    $var wire 32 $! LINE_SIZE [31:0] $end
    $var wire 32 %! MEMORY_LINES [31:0] $end
    $var wire 32 *! NUM_SETS_CACHE [31:0] $end
    $var wire 32 )! OFFSET [31:0] $end
    $var wire 32 (! TAG [31:0] $end
    $var wire 32 ?! VALID_BIT_WAY_0 [31:0] $end
    $var wire 32 @! VALID_BIT_WAY_1 [31:0] $end
    $var wire 32 +! WIDE_CACHE_LINE [31:0] $end
    $var wire 32 %! WORDS_PER_LINES [31:0] $end
    $var wire 32 #! WORD_SIZE [31:0] $end
    $var wire  1 N addr_ask $end
    $var wire 32 M addr_asked [31:0] $end
    $var wire 32 C addr_o [31:0] $end
    $var wire  1 I ask_memory_o $end
    $var wire 307 O cache_men(0) [306:0] $end
    $var wire 307 Y cache_men(1) [306:0] $end
    $var wire  1 !! clk_i $end
    $var wire 128 E data_i [127:0] $end
    $var wire 32 K instruction_register_o [31:0] $end
    $var wire 32 J nrm0_o [31:0] $end
    $var wire 32 c rm0 [31:0] $end
    $var wire  1 "! rstn_i $end
    $var wire  1 D valid_input_i $end
    $var wire  1 L valid_o $end
    $scope module unnamedblk1 $end
     $var wire 32 d i [31:0] $end
    $upscope $end
   $upscope $end
   $scope module inst_MEM $end
    $var wire 32 $! LINE_SIZE [31:0] $end
    $var wire 32 #! MEMORY_LINES [31:0] $end
    $var wire 32 %! WORDS_PER_LINES [31:0] $end
    $var wire 32 #! WORD_SIZE [31:0] $end
    $var wire 32 C addr_i [31:0] $end
    $var wire  1 !! clk_i $end
    $var wire 128 E data_i [127:0] $end
    $var wire 128 E data_o [127:0] $end
    $var wire 128 e data_o_0 [127:0] $end
    $var wire 128 i data_o_1 [127:0] $end
    $var wire 128 m data_o_2 [127:0] $end
    $var wire 128 q data_o_3 [127:0] $end
    $var wire 128 u data_o_4 [127:0] $end
    $var wire 32 # main_mem(0) [31:0] $end
    $var wire 32 $ main_mem(1) [31:0] $end
    $var wire 32 - main_mem(10) [31:0] $end
    $var wire 32 . main_mem(11) [31:0] $end
    $var wire 32 / main_mem(12) [31:0] $end
    $var wire 32 0 main_mem(13) [31:0] $end
    $var wire 32 1 main_mem(14) [31:0] $end
    $var wire 32 2 main_mem(15) [31:0] $end
    $var wire 32 3 main_mem(16) [31:0] $end
    $var wire 32 4 main_mem(17) [31:0] $end
    $var wire 32 5 main_mem(18) [31:0] $end
    $var wire 32 6 main_mem(19) [31:0] $end
    $var wire 32 % main_mem(2) [31:0] $end
    $var wire 32 7 main_mem(20) [31:0] $end
    $var wire 32 8 main_mem(21) [31:0] $end
    $var wire 32 9 main_mem(22) [31:0] $end
    $var wire 32 : main_mem(23) [31:0] $end
    $var wire 32 ; main_mem(24) [31:0] $end
    $var wire 32 < main_mem(25) [31:0] $end
    $var wire 32 = main_mem(26) [31:0] $end
    $var wire 32 > main_mem(27) [31:0] $end
    $var wire 32 ? main_mem(28) [31:0] $end
    $var wire 32 @ main_mem(29) [31:0] $end
    $var wire 32 & main_mem(3) [31:0] $end
    $var wire 32 A main_mem(30) [31:0] $end
    $var wire 32 B main_mem(31) [31:0] $end
    $var wire 32 ' main_mem(4) [31:0] $end
    $var wire 32 ( main_mem(5) [31:0] $end
    $var wire 32 ) main_mem(6) [31:0] $end
    $var wire 32 * main_mem(7) [31:0] $end
    $var wire 32 + main_mem(8) [31:0] $end
    $var wire 32 , main_mem(9) [31:0] $end
    $var wire  1 "! rstn_i $end
    $var wire  1 I strobe_i $end
    $var wire  1 y valid_0 $end
    $var wire  1 z valid_1 $end
    $var wire  1 { valid_2 $end
    $var wire  1 | valid_3 $end
    $var wire  1 } valid_4 $end
    $var wire  1 D valid_data_o $end
    $var wire  1 '! we_i $end
    $scope module unnamedblk1 $end
     $var wire 32 ~ i [31:0] $end
    $upscope $end
   $upscope $end
  $upscope $end
 $upscope $end
$enddefinitions $end


#0
b00000000000000000000010000000000 #
b00000000000100000000010000000000 $
b00000000000000000000010000000000 %
b00000000000100000000010000000000 &
b00000000000000000000010000000000 '
b00000000000100000000010000000000 (
b00000000000000000000010000000000 )
b00000000000100000000010000000000 *
b00000000000000000000010000000000 +
b00000000000100000000010000000000 ,
b00000000000000000000010000000000 -
b00000000000100000000010000000000 .
b00000000000000000000010000000000 /
b00000000000100000000010000000000 0
b00000000000000000000010000000000 1
b00000000000100000000010000000000 2
b00000000000000000000010000000000 3
b00000000000100000000010000000000 4
b00000000000000000000010000000000 5
b00000000000100000000010000000000 6
b00000000000000000000010000000000 7
b00000000000100000000010000000000 8
b00000000000000000000010000000000 9
b00000000000100000000010000000000 :
b00000000000000000000010000000000 ;
b00000000000100000000010000000000 <
b00000000000000000000010000000000 =
b00000000000100000000010000000000 >
b00000000000000000000010000000000 ?
b00000000000100000000010000000000 @
b00000000000000000000010000000000 A
b00000000000000000000000000000000 B
b00000000000000000000000000000000 C
0D
b00000000000000000000000000000000000000000000000000000000000000000000000000000000000000000000000000000000000000000000000000000000 E
1I
b00000000000000000000000000000000 J
b00000000000000000000000000000000 K
0L
b00000000000000000000000000000000 M
1N
b0000000000000000000000000000000000000000000000000000000000000000000000000000000000000000000000000000000000000000000000000000000000000000000000000000000000000000000000000000000000000000000000000000000000000000000000000000000000000000000000000000000000000000000000000000000000000000000000000000000000000000000 O
b0000000000000000000000000000000000000000000000000000000000000000000000000000000000000000000000000000000000000000000000000000000000000000000000000000000000000000000000000000000000000000000000000000000000000000000000000000000000000000000000000000000000000000000000000000000000000000000000000000000000000000000 Y
b00000000000000000000000000000000 c
b00000000000000000000000000000000 d
b00000000000000000000000000000000000000000000000000000000000000000000000000000000000000000000000000000000000000000000000000000000 e
b00000000000000000000000000000000000000000000000000000000000000000000000000000000000000000000000000000000000000000000000000000000 i
b00000000000000000000000000000000000000000000000000000000000000000000000000000000000000000000000000000000000000000000000000000000 m
b00000000000000000000000000000000000000000000000000000000000000000000000000000000000000000000000000000000000000000000000000000000 q
b00000000000000000000000000000000000000000000000000000000000000000000000000000000000000000000000000000000000000000000000000000000 u
0y
0z
0{
0|
0}
b00000000000000000000000000000000 ~
1!!
1"!
b00000000000000000000000000100000 #!
b00000000000000000000000010000000 $!
b00000000000000000000000000000100 %!
b00000000000000000000000000000101 &!
0'!
b00000000000000000000000000011000 (!
b00000000000000000000000000000111 )!
b00000000000000000000000000000010 *!
b00000000000000000000000100110011 +!
b00000000000000000000000010011011 ,!
b00000000000000000000000000011001 -!
b00000000000000000000000010110010 .!
b00000000000000000000000000011010 /!
b00000000000000000000000000111001 0!
b00000000000000000000000000111010 1!
b00000000000000000000000001011001 2!
b00000000000000000000000001011010 3!
b00000000000000000000000001111001 4!
b00000000000000000000000001111010 5!
b00000000000000000000000010011001 6!
b00000000000000000000000010110011 7!
b00000000000000000000000011010010 8!
b00000000000000000000000011010011 9!
b00000000000000000000000011110010 :!
b00000000000000000000000011110011 ;!
b00000000000000000000000100010010 <!
b00000000000000000000000100010011 =!
b00000000000000000000000100110010 >!
b00000000000000000000000000000001 ?!
b00000000000000000000000010011010 @!
#1
0!!
#2
0I
b00000000000100000000010000000000000000000000000000000100000000000000000000010000000001000000000000000000000000000000010000000000 e
1y
1!!
#3
0!!
#4
b00000000000100000000010000000000000000000000000000000100000000000000000000010000000001000000000000000000000000000000010000000000 i
0y
1z
1!!
#5
0!!
#6
b00000000000100000000010000000000000000000000000000000100000000000000000000010000000001000000000000000000000000000000010000000000 m
0z
1{
1!!
#7
0!!
#8
b00000000000100000000010000000000000000000000000000000100000000000000000000010000000001000000000000000000000000000000010000000000 q
0{
1|
1!!
#9
0!!
#10
b00000000000100000000010000000000000000000000000000000100000000000000000000010000000001000000000000000000000000000000010000000000 u
0|
1}
1!!
#11
0!!
#12
1D
b00000000000100000000010000000000000000000000000000000100000000000000000000010000000001000000000000000000000000000000010000000000 E
0}
1!!
#13
0!!
#14
0D
0N
b0000000000000000000000000000000000000000000000000000000000000000000000000000000000000000000000000000000000000000000000000000000000000000000000000000000000000000000010000000001000000000000000000000000000000010000000000000000000001000000000100000000000000000000000000000001000000000000000000000000000000000011 O
1!!
#15
0!!
#16
b00000000000000000000000000100000 J
b00000000000000000000010000000000 K
1L
b00000000000000000000000000100000 c
1!!
#17
0!!
#18
b00000000000000000000000001000000 J
b00000000000100000000010000000000 K
b00000000000000000000000001000000 c
1!!
#19
0!!
#20
b00000000000000000000000001100000 J
b00000000000000000000010000000000 K
b00000000000000000000000001100000 c
1!!
#21
0!!
#22
b00000000000000000000000010000000 J
b00000000000100000000010000000000 K
b00000000000000000000000010000000 c
1!!
#23
0!!
#24
b00000000000000000000000010000000 C
1I
0L
b00000000000000000000000010000000 M
1N
1!!
#25
0!!
#26
0I
1y
1!!
#27
0!!
#28
0y
1z
1!!
#29
0!!
#30
0z
1{
1!!
#31
0!!
#32
0{
1|
1!!
#33
0!!
#34
0|
1}
1!!
#35
0!!
#36
1D
0}
1!!
#37
0!!
#38
0D
0N
b0000000000000000000000000000000000000000000000000000000000000000000000000000000000000000000000000000000000000000000000000000000000000000000000000000000000000000000010000000001000000000000000000000000000000010000000000000000000001000000000100000000000000000000000000000001000000000000000000000000000000000011 Y
1!!
#39
0!!
#40
b00000000000000000000000010100000 J
b00000000000000000000010000000000 K
1L
b00000000000000000000000010100000 c
1!!
#41
0!!
#42
b00000000000000000000000011000000 J
b00000000000100000000010000000000 K
b00000000000000000000000011000000 c
1!!
#43
0!!
#44
b00000000000000000000000011100000 J
b00000000000000000000010000000000 K
b00000000000000000000000011100000 c
1!!
#45
0!!
#46
b00000000000000000000000100000000 J
b00000000000100000000010000000000 K
b00000000000000000000000100000000 c
1!!
