modules/modules_base/hdl/defines.vh
//-------------------------------------------------
// Generated defines                               
//-------------------------------------------------

`define SIM 1

modules/modules_base/hdl/memory.v
`default_nettype none
//-----------------------------------------------------
// Project Name : a.out
// Function     : Memory emulator for the processor
// Description  : Memory simulation using a 32 bit size and a LINE_SIZE of 128 with a delay in 3 cycles for geting the data
// Coder        : Jaquer AND Barrera

//***Headers***
`include "defines.vh"
//***Module***
module memory #(
        parameter integer WORD_SIZE = 32,
        parameter integer WORDS_PER_LINES = 4,
        parameter integer LINE_SIZE = 128,
        parameter integer MEMORY_LINES = 32
    )
    (
        input  clk_i ,
        input  rstn_i ,
        input  we_i ,
        input  strobe_i ,
        input  [LINE_SIZE - 1 : 0] data_i ,
        input  [WORD_SIZE - 1 : 0] addr_i ,
        output [LINE_SIZE - 1 : 0] data_o ,
        output valid_data_o 
    );

//***Interal logic generated by compiler***  


//***Dumped Internal logic***
    reg [WORD_SIZE-1:0] main_mem [0:MEMORY_LINES-1];
    reg [LINE_SIZE-1:0] data_o_0;
    reg [LINE_SIZE-1:0] data_o_1;
    reg [LINE_SIZE-1:0] data_o_2;
    reg [LINE_SIZE-1:0] data_o_3; 
    reg [LINE_SIZE-1:0] data_o_4;    
    reg valid_0; 
    reg valid_1;
    reg valid_2;
    reg valid_3;
    reg valid_4;
    `ifdef SIM
        initial begin
        $display("Loading rom.");
        $readmemh("../../../memory.hex", main_mem);
        $display("Rom loaded");
        end
    `endif

    always @(posedge clk_i) begin
        // data_o_0 <= {WORD_SIZE{1'b0}};
        valid_0 <=0;                           
        if (!rstn_i) begin                                       
            // reset                                            
            integer i;         
            /* verilator lint_off BLKLOOPINIT*/                                 
            for(i=0;i<MEMORY_LINES; i=i+1) begin                 
                main_mem[i] <= {WORD_SIZE{1'b0}};                
            end   
            /* verilator lint_on BLKLOOPINIT*/                                             
                                                                
        end                                                  
        else if (we_i) begin                                 
            main_mem[addr_i] <= data_i[31:0] ;                         
                                                                
        end else if (strobe_i) begin                        
            data_o_0[31:0] <=  main_mem[addr_i>>5]; 
            data_o_0[63:32] <= main_mem[(addr_i>>5)+1];
            data_o_0[95:64] <= main_mem[(addr_i>>5)+2];          
            data_o_0[127:96] <= main_mem[(addr_i>>5)+3]; 
            //data_o_0[31:0] <=  main_mem[addr_i];           
            //data_o_0[63:32] <= main_mem[addr_i + 2'b01];
            //data_o_0[95:64] <= main_mem[addr_i + 2'b10];                 
            //data_o_0[127:96] <= main_mem[addr_i + 2'b11]; 
            valid_0 <= 1;                    
                                                                
        end
        data_o <= data_o_4;
        valid_data_o <= valid_4;
        data_o_4 <=  data_o_3;
        valid_4 <= valid_3;
        data_o_3 <= data_o_2;
        valid_3 <= valid_2;
        data_o_2 <= data_o_1;
        valid_2 <= valid_1;
        data_o_1 <= data_o_0;
        valid_1 <= valid_0;

    end   
    
//***Handcrafted Internal logic*** 
//TODO
endmodule

modules/modules/hdl/random_number_generator.v
`default_nettype none
//-----------------------------------------------------
// Project Name : a.out
// Function     : Generate random number
// Description  : Generate a random number and send by the output

//***Headers***
`include "defines.vh"
//***Module***
module random_number_generator #(
        parameter integer WORD_SIZE = 32
    )
    (
        input  clk_i ,
        output [WORD_SIZE - 1 : 0] output_number_o 
    );

//***Interal logic generated by compiler***  


//***Dumped Internal logic***
    assign output_number_o =  32'b00000001010000100100101111001001;
    
//***Handcrafted Internal logic*** 
//TODO
endmodule

modules/modules_base/hdl/hash_cache_function.v
`default_nettype none
//-----------------------------------------------------
// Project Name : a.out
// Function     : Generate the hash function
// Description  : Generate all function

//***Headers***
`include "defines.vh"
//***Module***
module hash_cache_function #(
        parameter integer WORD_SIZE = 32
    )
    (
        input  clk_i ,
        input  [WORD_SIZE - 1 : 0] addr_i ,
        output line_index_o 
    );

//***Interal logic generated by compiler***  
//***Auxiliar Wires***  
    wire [WORD_SIZE - 1 : 0] random_number_w; // Auxiliar Wire

    random_number_generator #(
        .WORD_SIZE (32)
    )
    inst_RNG(
        .clk_i                  (clk_i ),
        .output_number_o        (random_number_w)
    );


//***Dumped Internal logic***
    reg [WORD_SIZE-1:0] rotate_0;
    reg [WORD_SIZE-1:0] rotate_1;
    reg [WORD_SIZE-1:0] rotate_2;
    reg [WORD_SIZE-1:0] rotate_3;
    reg [WORD_SIZE-1:0] rotate_4;
    reg [WORD_SIZE-1:0] rotate_5;
    wire [(WORD_SIZE*3)-1:0] output_xor_0;
    wire [48-1:0] output_xor_1;
    wire [24-1:0] output_xor_2;
    wire [12-1:0] output_xor_3;
    wire [6-1:0] output_xor_4;
    wire [3-1:0] output_xor_5;
    wire output_xor_6;
    

    assign output_xor_0 = {rotate_0,rotate_1,rotate_2} ^ {rotate_3,rotate_4,rotate_5};
    assign output_xor_1 = output_xor_0[95:48] ^ output_xor_0[47:0];
    assign output_xor_2 = output_xor_1[47:24] ^ output_xor_1[23:0];
    assign output_xor_3 = output_xor_2[23:12] ^ output_xor_2[11:0];
    assign output_xor_4 = output_xor_3[11:6] ^ output_xor_3[5:0];
    assign output_xor_5 = output_xor_4[5:3] ^ output_xor_4[2:0];
    assign line_index_o = output_xor_5[2] ^ output_xor_5[1] ^ output_xor_5[0];

    always @(posedge clk_i) begin


    rotate_0  <= (random_number_w >> addr_i[11:7]) | (random_number_w <<  (WORD_SIZE - {{27{1'b0}},addr_i[11:7]}));
    rotate_1  <= (random_number_w >> addr_i[16:12]) | (random_number_w <<  (WORD_SIZE - {{27{1'b0}},addr_i[16:12]}));
    rotate_2  <= (random_number_w >> addr_i[21:17]) | (random_number_w <<  (WORD_SIZE - {{27{1'b0}},addr_i[21:17]}));

    rotate_3  <= ({addr_i[31:7],7'b0000000} >> random_number_w[4:0]) | ({addr_i[31:7],7'b0000000} <<  (WORD_SIZE - {{27{1'b0}},random_number_w[4:0]}));
    rotate_4  <= ({addr_i[31:7],7'b0000000} >> random_number_w[9:5]) | ({addr_i[31:7],7'b0000000} <<  (WORD_SIZE - {{27{1'b0}},random_number_w[9:5]}));
    rotate_5  <= ({addr_i[31:7],7'b0000000} >> random_number_w[14:10]) | ({addr_i[31:7],7'b0000000} <<  (WORD_SIZE - {{27{1'b0}},random_number_w[14:10]}));



    end


    
//***Handcrafted Internal logic*** 
//TODO
endmodule

modules/modules_base/hdl/fetch.v
`default_nettype none
//-----------------------------------------------------
// Project Name : a.out
// Function     : fetch instruction form the I-cache
// Description  : This module is for the feching instruction from the I-cahe in order to provided to the processor
// Coder        : Jaquer AND Barrera

//***Headers***
`include "defines.vh"
//***Module***
module fetch #(
        parameter integer WORD_SIZE = 32,
        parameter integer LINE_SIZE = 128,
        parameter integer WORDS_PER_LINES = 4,
        parameter integer MEMORY_LINES = 4,
        parameter integer TAG = 24,
        parameter integer OFFSET = 7
    )
    (
        input  clk_i ,
        input  rstn_i ,
        input  [LINE_SIZE - 1 : 0] data_i ,
        input  valid_input_i ,
        output [WORD_SIZE - 1 : 0] nrm0_o ,
        output [WORD_SIZE - 1 : 0] addr_o ,
        output [WORD_SIZE - 1 : 0] instruction_register_o ,
        output ask_memory_o ,
        output valid_o 
    );

//***Interal logic generated by compiler***  
//***Auxiliar Wires***  
    wire line_index_w; // Auxiliar Wire

    hash_cache_function #(
        .WORD_SIZE (32)
    )
    inst_hcf(
        .clk_i                (clk_i ),
        .addr_i               (addr_o ),
        .line_index_o         (line_index_w)
    );


//***Dumped Internal logic***
    localparam NUM_SETS_CACHE = ((LINE_SIZE * MEMORY_LINES)/(LINE_SIZE *2));
    localparam WIDE_CACHE_LINE = (TAG*2 + LINE_SIZE*2 + 3);
    localparam INIT_POS_TAG_WAY_1 = 2;
    localparam INIT_POS_TAG_WAY_2 = 3+TAG+LINE_SIZE;
    localparam END_POS_TAG_WAY_1 = TAG+1;
    localparam END_POS_TAG_WAY_2 = TAG+2+LINE_SIZE+TAG;
    // params for cache word acces
    // way 1
    localparam INIT_POS_WORD_1_WAY_1 = TAG+2;
    localparam END_POS_WORD_1_WAY_1 = TAG+2+WORD_SIZE-1;
    localparam INIT_POS_WORD_2_WAY_1 = TAG+WORD_SIZE+2;
    localparam END_POS_WORD_2_WAY_1 = TAG+2+WORD_SIZE+WORD_SIZE-1;
    localparam INIT_POS_WORD_3_WAY_1 = TAG+WORD_SIZE+WORD_SIZE+2;
    localparam END_POS_WORD_3_WAY_1 = TAG+2+WORD_SIZE+WORD_SIZE+WORD_SIZE-1;
    localparam INIT_POS_WORD_4_WAY_1 = TAG+WORD_SIZE+WORD_SIZE+WORD_SIZE+2;
    localparam END_POS_WORD_4_WAY_1 = TAG+2+WORD_SIZE+WORD_SIZE+WORD_SIZE+WORD_SIZE-1;
    
    // way 2
    localparam INIT_POS_WORD_1_WAY_2 = TAG+TAG+3+LINE_SIZE;
    localparam END_POS_WORD_1_WAY_2 = TAG+3+TAG+LINE_SIZE+WORD_SIZE-1;
    localparam INIT_POS_WORD_2_WAY_2 = TAG+TAG+WORD_SIZE+3+LINE_SIZE;
    localparam END_POS_WORD_2_WAY_2 = TAG+3+TAG+LINE_SIZE+WORD_SIZE+WORD_SIZE-1;
    localparam INIT_POS_WORD_3_WAY_2 = TAG+TAG+WORD_SIZE+WORD_SIZE+3+LINE_SIZE;
    localparam END_POS_WORD_3_WAY_2 = TAG+3+TAG+LINE_SIZE+WORD_SIZE+WORD_SIZE+WORD_SIZE-1;
    localparam INIT_POS_WORD_4_WAY_2 = TAG+TAG+WORD_SIZE+WORD_SIZE+WORD_SIZE+3+LINE_SIZE;
    localparam END_POS_WORD_4_WAY_2 = TAG+3+TAG+LINE_SIZE+WORD_SIZE+WORD_SIZE+WORD_SIZE+WORD_SIZE-1;
    
    // block 0 --> block in way 0
    localparam INIT_POS_LINE_0 = TAG+2;
    localparam END_POS_LINE_0 = TAG+2+LINE_SIZE-1;
    localparam INIT_POS_TAG_LINE_0 = 2;
    localparam END_POS_TAG_LINE_0 = TAG+1;
    localparam VALID_BIT_WAY_0 = 1;

    // block 1

    localparam INIT_POS_LINE_1 = TAG+TAG+3+LINE_SIZE;
    localparam END_POS_LINE_1 = TAG+3+TAG+LINE_SIZE+LINE_SIZE-1;
    localparam INIT_POS_TAG_LINE_1 = 3+TAG+LINE_SIZE;
    localparam END_POS_TAG_LINE_1 = TAG+2+LINE_SIZE+TAG;
    localparam VALID_BIT_WAY_1 = TAG+2+LINE_SIZE;

    reg [WORD_SIZE-1:0]addr_asked;
    reg addr_ask;
    reg [WIDE_CACHE_LINE-1:0] cache_men [0:NUM_SETS_CACHE-1];

    reg [WORD_SIZE-1:0] rm0;


    //assign next_pc_w = !rstn_i ? {WORD_SIZE{1'b0}} : valid_o ? rm0 + 32 :  rm0;
    always @(posedge clk_i) begin

        ask_memory_o <= 1'b0;
        if (!rstn_i) begin                                       
            // reset                                            
            integer i;         
            /* verilator lint_off BLKLOOPINIT*/                                 
            for(i=0;i<NUM_SETS_CACHE; i=i+1) begin                 
                cache_men[i] <= {WIDE_CACHE_LINE{1'b0}};                
            end   
            /* verilator lint_on BLKLOOPINIT*/
            rm0 <= {WORD_SIZE{1'b0}};
        end
        else begin
            //rm0 <= next_pc_w;
            // take the rm0 and check if is in catch
            // check if is in way 1 or 0
            // check way 0 and valid 23/7
            if(cache_men[rm0[OFFSET]][END_POS_TAG_WAY_1:INIT_POS_TAG_WAY_1] == rm0[WORD_SIZE-1:OFFSET+1] && cache_men[rm0[OFFSET]][VALID_BIT_WAY_0]) begin
                // hit in way 0
                // rm0[WORD_SIZE-1:TAG] is offset
                valid_o <= 1;
                rm0 <= rm0 +32;
                nrm0_o <= rm0 +32;

                if(rm0[OFFSET-1:OFFSET-2] == 2'b00) begin
                    instruction_register_o <= cache_men[rm0[OFFSET]][END_POS_WORD_1_WAY_1:INIT_POS_WORD_1_WAY_1];
                end
                else if (rm0[OFFSET-1:OFFSET-2] == 2'b01) begin
                    instruction_register_o <= cache_men[rm0[OFFSET]][END_POS_WORD_2_WAY_1:INIT_POS_WORD_2_WAY_1];
                end

                else if (rm0[OFFSET-1:OFFSET-2] == 2'b10) begin
                    instruction_register_o <= cache_men[rm0[OFFSET]][END_POS_WORD_3_WAY_1:INIT_POS_WORD_3_WAY_1];
                end
                else if (rm0[OFFSET-1:OFFSET-2] == 2'b11)begin
                    instruction_register_o <= cache_men[rm0[OFFSET]][END_POS_WORD_4_WAY_1:INIT_POS_WORD_4_WAY_1];
                end


                
            end
            // check way 1 and valid 
            else if(cache_men[rm0[OFFSET]][END_POS_TAG_WAY_2:INIT_POS_TAG_WAY_2] == rm0[WORD_SIZE-1:OFFSET+1] && cache_men[rm0[OFFSET]][VALID_BIT_WAY_1]) begin
                // hit in way 1
                valid_o <= 1;
                rm0 <= rm0 +32;
                nrm0_o <= rm0 +32;

                if(rm0[OFFSET-1:OFFSET-2] == 2'b00) begin
                    instruction_register_o <= cache_men[rm0[OFFSET]][END_POS_WORD_1_WAY_2:INIT_POS_WORD_1_WAY_2];
                end
                else if (rm0[OFFSET-1:OFFSET-2] == 2'b01) begin
                    instruction_register_o <= cache_men[rm0[OFFSET]][END_POS_WORD_2_WAY_2:INIT_POS_WORD_2_WAY_2];
                end

                else if (rm0[OFFSET-1:OFFSET-2] == 2'b10) begin
                    instruction_register_o <= cache_men[rm0[OFFSET]][END_POS_WORD_3_WAY_2:INIT_POS_WORD_3_WAY_2];
                end
                else if (rm0[OFFSET-1:OFFSET-2] == 2'b11)begin
                    instruction_register_o <= cache_men[rm0[OFFSET]][END_POS_WORD_4_WAY_2:INIT_POS_WORD_4_WAY_2];
                end

                
            end
            else if (addr_ask && valid_input_i) begin
                if(cache_men[addr_asked[OFFSET]][0]) begin
                    // LRU == 1 replace way 1
                    // replace LRU
                    cache_men[addr_asked[OFFSET]][0] <= 1'b0;
                    // store block in way 1
                    cache_men[addr_asked[OFFSET]][END_POS_LINE_1:INIT_POS_LINE_1] <= data_i;
                    // set the valid bit
                    cache_men[addr_asked[OFFSET]][VALID_BIT_WAY_1] <= 1'b1;
                    // store the tag
                    cache_men[addr_asked[OFFSET]][END_POS_TAG_LINE_1:INIT_POS_TAG_LINE_1] <= addr_asked[WORD_SIZE-1:OFFSET+1];
                    // set the ask
                    addr_ask <= 1'b0;

                end
                else begin
                    // LRU == 0 replace way 0
                    // replace LRU
                    cache_men[addr_asked[OFFSET]][0] <= 1'b1;
                    // store block in way 0
                    cache_men[addr_asked[OFFSET]][END_POS_LINE_0:INIT_POS_LINE_0] <= data_i;
                    // set bit to valid
                    cache_men[addr_asked[OFFSET]][VALID_BIT_WAY_0] <= 1'b1;
                    //store the tag
                    cache_men[addr_asked[OFFSET]][END_POS_TAG_LINE_0:INIT_POS_TAG_LINE_0] <= addr_asked[WORD_SIZE-1:OFFSET+1];
                    // set the ask
                    addr_ask <= 1'b0;

                end
            end
            else if (addr_ask && rm0 == addr_asked) begin
                // same addr ask 
                valid_o <= 0;
            end
            else begin
                // Mis go to main memory
                addr_asked <= rm0;
                addr_ask <= 1'b1;
                valid_o <= 0;
                addr_o <= rm0;
                ask_memory_o <= 1'b1;

            end 
        end

    end
    //assign next_pc_w = !rstn_i ? {WORD_SIZE{1'b0}} : valid_o ? rm0 + 32 :  rm0;
    //assign nrm0_o = next_pc_w;
    
//***Handcrafted Internal logic*** 
//TODO
endmodule

modules/modules_base/hdl/processor.v
`default_nettype none
//-----------------------------------------------------
// Project Name : a.out
// Function     : Main processor 
// Description  : This is the main processor
// Coder        : Jaquer AND Barrera

//***Headers***
`include "defines.vh"
//***Module***
module processor #(
        parameter integer WORD_SIZE = 32,
        parameter integer REGISTERS = 32,
        parameter integer LINE_SIZE = 128,
        parameter integer ALUOP_SIZE = 4,
        parameter integer REGDIRSIZE = 5
    )
    (
        input  clk_i ,
        input  rstn_i 
    );

//***Interal logic generated by compiler***  
    wire [WORD_SIZE - 1 : 0] addr_IF_MEM; // wiring between addr_o of module IF and addr_i of module MEM
    wire valid_data_MEM_IF; // wiring between valid_data_o of module MEM and valid_input_i of module IF
//***Auxiliar Wires***  
    wire [LINE_SIZE - 1 : 0] mem_data_bus_w; // Auxiliar Wire
    wire write_data_bus_mem_w; // Auxiliar Wire
    wire strobe_main_memory_w; // Auxiliar Wire

    fetch #(
        .WORD_SIZE (32),
        .LINE_SIZE (128),
        .WORDS_PER_LINES (4),
        .MEMORY_LINES (4),
        .TAG (24),
        .OFFSET (7)
    )
    inst_IF(
        .clk_i                        (clk_i ),
        .rstn_i                       (rstn_i ),
        .data_i                       (mem_data_bus_w),
        .valid_input_i                (valid_data_MEM_IF),
        .nrm0_o                       (),
        .addr_o                       (addr_IF_MEM),
        .instruction_register_o       (),
        .ask_memory_o                 (strobe_main_memory_w),
        .valid_o                      ()
    );

    memory #(
        .WORD_SIZE (32),
        .WORDS_PER_LINES (4),
        .LINE_SIZE (128),
        .MEMORY_LINES (32)
    )
    inst_MEM(
        .clk_i                (clk_i ),
        .rstn_i               (rstn_i ),
        .we_i                 (write_data_bus_mem_w),
        .strobe_i             (strobe_main_memory_w),
        .data_i               (mem_data_bus_w),
        .addr_i               (addr_IF_MEM),
        .data_o               (mem_data_bus_w),
        .valid_data_o         (valid_data_MEM_IF)
    );


//***Handcrafted Internal logic*** 
//TODO
endmodule

modules/modules_base/tb/verilator/obj_dir/Vprocessor.vcd
$version Generated by VerilatedVcd $end
$date Mon Nov 11 17:48:28 2019
 $end
$timescale   1ns $end

 $scope module TOP $end
  $var wire  1 1! clk_i $end
  $var wire  1 2! rstn_i $end
  $scope module processor $end
   $var wire 32 5! ALUOP_SIZE [31:0] $end
   $var wire 32 4! LINE_SIZE [31:0] $end
   $var wire 32 6! REGDIRSIZE [31:0] $end
   $var wire 32 3! REGISTERS [31:0] $end
   $var wire 32 3! WORD_SIZE [31:0] $end
   $var wire 32 M addr_IF_MEM [31:0] $end
   $var wire  1 1! clk_i $end
   $var wire 128 O mem_data_bus_w [127:0] $end
   $var wire  1 2! rstn_i $end
   $var wire  1 S strobe_main_memory_w $end
   $var wire  1 N valid_data_MEM_IF $end
   $var wire  1 7! write_data_bus_mem_w $end
   $scope module inst_IF $end
    $var wire 32 F! END_POS_LINE_0 [31:0] $end
    $var wire 32 N! END_POS_LINE_1 [31:0] $end
    $var wire 32 =! END_POS_TAG_LINE_0 [31:0] $end
    $var wire 32 >! END_POS_TAG_LINE_1 [31:0] $end
    $var wire 32 =! END_POS_TAG_WAY_1 [31:0] $end
    $var wire 32 >! END_POS_TAG_WAY_2 [31:0] $end
    $var wire 32 @! END_POS_WORD_1_WAY_1 [31:0] $end
    $var wire 32 H! END_POS_WORD_1_WAY_2 [31:0] $end
    $var wire 32 B! END_POS_WORD_2_WAY_1 [31:0] $end
    $var wire 32 J! END_POS_WORD_2_WAY_2 [31:0] $end
    $var wire 32 D! END_POS_WORD_3_WAY_1 [31:0] $end
    $var wire 32 L! END_POS_WORD_3_WAY_2 [31:0] $end
    $var wire 32 F! END_POS_WORD_4_WAY_1 [31:0] $end
    $var wire 32 N! END_POS_WORD_4_WAY_2 [31:0] $end
    $var wire 32 ?! INIT_POS_LINE_0 [31:0] $end
    $var wire 32 G! INIT_POS_LINE_1 [31:0] $end
    $var wire 32 :! INIT_POS_TAG_LINE_0 [31:0] $end
    $var wire 32 <! INIT_POS_TAG_LINE_1 [31:0] $end
    $var wire 32 :! INIT_POS_TAG_WAY_1 [31:0] $end
    $var wire 32 <! INIT_POS_TAG_WAY_2 [31:0] $end
    $var wire 32 ?! INIT_POS_WORD_1_WAY_1 [31:0] $end
    $var wire 32 G! INIT_POS_WORD_1_WAY_2 [31:0] $end
    $var wire 32 A! INIT_POS_WORD_2_WAY_1 [31:0] $end
    $var wire 32 I! INIT_POS_WORD_2_WAY_2 [31:0] $end
    $var wire 32 C! INIT_POS_WORD_3_WAY_1 [31:0] $end
    $var wire 32 K! INIT_POS_WORD_3_WAY_2 [31:0] $end
    $var wire 32 E! INIT_POS_WORD_4_WAY_1 [31:0] $end
    $var wire 32 M! INIT_POS_WORD_4_WAY_2 [31:0] $end
    $var wire 32 4! LINE_SIZE [31:0] $end
    $var wire 32 5! MEMORY_LINES [31:0] $end
    $var wire 32 :! NUM_SETS_CACHE [31:0] $end
    $var wire 32 9! OFFSET [31:0] $end
    $var wire 32 8! TAG [31:0] $end
    $var wire 32 O! VALID_BIT_WAY_0 [31:0] $end
    $var wire 32 P! VALID_BIT_WAY_1 [31:0] $end
    $var wire 32 ;! WIDE_CACHE_LINE [31:0] $end
    $var wire 32 5! WORDS_PER_LINES [31:0] $end
    $var wire 32 3! WORD_SIZE [31:0] $end
    $var wire  1 X addr_ask $end
    $var wire 32 W addr_asked [31:0] $end
    $var wire 32 M addr_o [31:0] $end
    $var wire  1 S ask_memory_o $end
    $var wire 307 Y cache_men(0) [306:0] $end
    $var wire 307 c cache_men(1) [306:0] $end
    $var wire  1 1! clk_i $end
    $var wire 128 O data_i [127:0] $end
    $var wire 32 U instruction_register_o [31:0] $end
    $var wire  1 # line_index_w $end
    $var wire 32 T nrm0_o [31:0] $end
    $var wire 32 m rm0 [31:0] $end
    $var wire  1 2! rstn_i $end
    $var wire  1 N valid_input_i $end
    $var wire  1 V valid_o $end
    $scope module inst_hcf $end
     $var wire 32 3! WORD_SIZE [31:0] $end
     $var wire 32 M addr_i [31:0] $end
     $var wire  1 1! clk_i $end
     $var wire  1 # line_index_o $end
     $var wire 96 $ output_xor_0 [95:0] $end
     $var wire 48 ' output_xor_1 [47:0] $end
     $var wire 24 ) output_xor_2 [23:0] $end
     $var wire 12 * output_xor_3 [11:0] $end
     $var wire  6 + output_xor_4 [5:0] $end
     $var wire  3 , output_xor_5 [2:0] $end
     $var wire  1 R! output_xor_6 $end
     $var wire 32 Q! random_number_w [31:0] $end
     $var wire 32 o rotate_0 [31:0] $end
     $var wire 32 p rotate_1 [31:0] $end
     $var wire 32 q rotate_2 [31:0] $end
     $var wire 32 r rotate_3 [31:0] $end
     $var wire 32 s rotate_4 [31:0] $end
     $var wire 32 t rotate_5 [31:0] $end
     $scope module inst_RNG $end
      $var wire 32 3! WORD_SIZE [31:0] $end
      $var wire  1 1! clk_i $end
      $var wire 32 Q! output_number_o [31:0] $end
     $upscope $end
    $upscope $end
    $scope module unnamedblk1 $end
     $var wire 32 n i [31:0] $end
    $upscope $end
   $upscope $end
   $scope module inst_MEM $end
    $var wire 32 4! LINE_SIZE [31:0] $end
    $var wire 32 3! MEMORY_LINES [31:0] $end
    $var wire 32 5! WORDS_PER_LINES [31:0] $end
    $var wire 32 3! WORD_SIZE [31:0] $end
    $var wire 32 M addr_i [31:0] $end
    $var wire  1 1! clk_i $end
    $var wire 128 O data_i [127:0] $end
    $var wire 128 O data_o [127:0] $end
    $var wire 128 u data_o_0 [127:0] $end
    $var wire 128 y data_o_1 [127:0] $end
    $var wire 128 } data_o_2 [127:0] $end
    $var wire 128 #! data_o_3 [127:0] $end
    $var wire 128 '! data_o_4 [127:0] $end
    $var wire 32 - main_mem(0) [31:0] $end
    $var wire 32 . main_mem(1) [31:0] $end
    $var wire 32 7 main_mem(10) [31:0] $end
    $var wire 32 8 main_mem(11) [31:0] $end
    $var wire 32 9 main_mem(12) [31:0] $end
    $var wire 32 : main_mem(13) [31:0] $end
    $var wire 32 ; main_mem(14) [31:0] $end
    $var wire 32 < main_mem(15) [31:0] $end
    $var wire 32 = main_mem(16) [31:0] $end
    $var wire 32 > main_mem(17) [31:0] $end
    $var wire 32 ? main_mem(18) [31:0] $end
    $var wire 32 @ main_mem(19) [31:0] $end
    $var wire 32 / main_mem(2) [31:0] $end
    $var wire 32 A main_mem(20) [31:0] $end
    $var wire 32 B main_mem(21) [31:0] $end
    $var wire 32 C main_mem(22) [31:0] $end
    $var wire 32 D main_mem(23) [31:0] $end
    $var wire 32 E main_mem(24) [31:0] $end
    $var wire 32 F main_mem(25) [31:0] $end
    $var wire 32 G main_mem(26) [31:0] $end
    $var wire 32 H main_mem(27) [31:0] $end
    $var wire 32 I main_mem(28) [31:0] $end
    $var wire 32 J main_mem(29) [31:0] $end
    $var wire 32 0 main_mem(3) [31:0] $end
    $var wire 32 K main_mem(30) [31:0] $end
    $var wire 32 L main_mem(31) [31:0] $end
    $var wire 32 1 main_mem(4) [31:0] $end
    $var wire 32 2 main_mem(5) [31:0] $end
    $var wire 32 3 main_mem(6) [31:0] $end
    $var wire 32 4 main_mem(7) [31:0] $end
    $var wire 32 5 main_mem(8) [31:0] $end
    $var wire 32 6 main_mem(9) [31:0] $end
    $var wire  1 2! rstn_i $end
    $var wire  1 S strobe_i $end
    $var wire  1 +! valid_0 $end
    $var wire  1 ,! valid_1 $end
    $var wire  1 -! valid_2 $end
    $var wire  1 .! valid_3 $end
    $var wire  1 /! valid_4 $end
    $var wire  1 N valid_data_o $end
    $var wire  1 7! we_i $end
    $scope module unnamedblk1 $end
     $var wire 32 0! i [31:0] $end
    $upscope $end
   $upscope $end
  $upscope $end
 $upscope $end
$enddefinitions $end


#0
1#
b000000010100001001001011110010010000000101000010010010111100100100000001010000100100101111001001 $
b010010101000101101001010100010110100101010001011 '
b110000011100000111000001 )
b110111011101 *
b101010 +
b111 ,
b00000000000000000000010000000000 -
b00000000000100000000010000000000 .
b00000000000000000000010000000000 /
b00000000000100000000010000000000 0
b00000000000000000000010000000000 1
b00000000000100000000010000000000 2
b00000000000000000000010000000000 3
b00000000000100000000010000000000 4
b00000000000000000000010000000000 5
b00000000000100000000010000000000 6
b00000000000000000000010000000000 7
b00000000000100000000010000000000 8
b00000000000000000000010000000000 9
b00000000000100000000010000000000 :
b00000000000000000000010000000000 ;
b00000000000100000000010000000000 <
b00000000000000000000010000000000 =
b00000000000100000000010000000000 >
b00000000000000000000010000000000 ?
b00000000000100000000010000000000 @
b00000000000000000000010000000000 A
b00000000000100000000010000000000 B
b00000000000000000000010000000000 C
b00000000000100000000010000000000 D
b00000000000000000000010000000000 E
b00000000000100000000010000000000 F
b00000000000000000000010000000000 G
b00000000000100000000010000000000 H
b00000000000000000000010000000000 I
b00000000000100000000010000000000 J
b00000000000000000000010000000000 K
b00000000000000000000000000000000 L
b00000000000000000000000000000000 M
0N
b00000000000000000000000000000000000000000000000000000000000000000000000000000000000000000000000000000000000000000000000000000000 O
1S
b00000000000000000000000000000000 T
b00000000000000000000000000000000 U
0V
b00000000000000000000000000000000 W
1X
b0000000000000000000000000000000000000000000000000000000000000000000000000000000000000000000000000000000000000000000000000000000000000000000000000000000000000000000000000000000000000000000000000000000000000000000000000000000000000000000000000000000000000000000000000000000000000000000000000000000000000000000 Y
b0000000000000000000000000000000000000000000000000000000000000000000000000000000000000000000000000000000000000000000000000000000000000000000000000000000000000000000000000000000000000000000000000000000000000000000000000000000000000000000000000000000000000000000000000000000000000000000000000000000000000000000 c
b00000000000000000000000000000000 m
b00000000000000000000000000000000 n
b00000001010000100100101111001001 o
b00000001010000100100101111001001 p
b00000001010000100100101111001001 q
b00000000000000000000000000000000 r
b00000000000000000000000000000000 s
b00000000000000000000000000000000 t
b00000000000000000000000000000000000000000000000000000000000000000000000000000000000000000000000000000000000000000000000000000000 u
b00000000000000000000000000000000000000000000000000000000000000000000000000000000000000000000000000000000000000000000000000000000 y
b00000000000000000000000000000000000000000000000000000000000000000000000000000000000000000000000000000000000000000000000000000000 }
b00000000000000000000000000000000000000000000000000000000000000000000000000000000000000000000000000000000000000000000000000000000 #!
b00000000000000000000000000000000000000000000000000000000000000000000000000000000000000000000000000000000000000000000000000000000 '!
0+!
0,!
0-!
0.!
0/!
b00000000000000000000000000000000 0!
11!
12!
b00000000000000000000000000100000 3!
b00000000000000000000000010000000 4!
b00000000000000000000000000000100 5!
b00000000000000000000000000000101 6!
07!
b00000000000000000000000000011000 8!
b00000000000000000000000000000111 9!
b00000000000000000000000000000010 :!
b00000000000000000000000100110011 ;!
b00000000000000000000000010011011 <!
b00000000000000000000000000011001 =!
b00000000000000000000000010110010 >!
b00000000000000000000000000011010 ?!
b00000000000000000000000000111001 @!
b00000000000000000000000000111010 A!
b00000000000000000000000001011001 B!
b00000000000000000000000001011010 C!
b00000000000000000000000001111001 D!
b00000000000000000000000001111010 E!
b00000000000000000000000010011001 F!
b00000000000000000000000010110011 G!
b00000000000000000000000011010010 H!
b00000000000000000000000011010011 I!
b00000000000000000000000011110010 J!
b00000000000000000000000011110011 K!
b00000000000000000000000100010010 L!
b00000000000000000000000100010011 M!
b00000000000000000000000100110010 N!
b00000000000000000000000000000001 O!
b00000000000000000000000010011010 P!
b00000001010000100100101111001001 Q!
0R!
#1
01!
#2
0S
b00000000000100000000010000000000000000000000000000000100000000000000000000010000000001000000000000000000000000000000010000000000 u
1+!
11!
#3
01!
#4
b00000000000100000000010000000000000000000000000000000100000000000000000000010000000001000000000000000000000000000000010000000000 y
0+!
1,!
11!
#5
01!
#6
b00000000000100000000010000000000000000000000000000000100000000000000000000010000000001000000000000000000000000000000010000000000 }
0,!
1-!
11!
#7
01!
#8
b00000000000100000000010000000000000000000000000000000100000000000000000000010000000001000000000000000000000000000000010000000000 #!
0-!
1.!
11!
#9
01!
#10
b00000000000100000000010000000000000000000000000000000100000000000000000000010000000001000000000000000000000000000000010000000000 '!
0.!
1/!
11!
#11
01!
#12
1N
b00000000000100000000010000000000000000000000000000000100000000000000000000010000000001000000000000000000000000000000010000000000 O
0/!
11!
#13
01!
#14
0N
0X
b0000000000000000000000000000000000000000000000000000000000000000000000000000000000000000000000000000000000000000000000000000000000000000000000000000000000000000000010000000001000000000000000000000000000000010000000000000000000001000000000100000000000000000000000000000001000000000000000000000000000000000011 Y
11!
#15
01!
#16
b00000000000000000000000000100000 T
b00000000000000000000010000000000 U
1V
b00000000000000000000000000100000 m
11!
#17
01!
